hek/__init__.py
hek/devicemanger.py
hek/exceptions.py
hek/getmac.py
hek/image.py
hek/info.py
hek/ipstuff.py
hek/network.py
hek/proxy.py
hek/record.py
hek/server.py
hek/torrequests.py
hek/wireless.py
hek-0.3.3.dist-info/LICENCE.txt
hek-0.3.3.dist-info/METADATA
hek-0.3.3.dist-info/WHEEL
hek-0.3.3.dist-info/top_level.txt
hek-0.3.3.dist-info/RECORD
