Metadata-Version: 2.1
Name: hek
Version: 0.3.3
Summary: A python library mostly used for pentesting and automate some tasks.
Home-page: https://github.com/greedalbadi/hek
Author: greed albadi
Author-email: greedalbadi@gmail.com
License: MIT
Project-URL: Source, https://github.com/greedalbadi/hek
Project-URL: Report Bugs, https://github.com/greedalbadi/hek/issues
Project-URL: Download, https://pypi.org/project/PyScaffold/#files
Project-URL: Documentation, https://github.com/greedalbadi/hek/blob/master/README.md
Keywords: python,pentesting,automation,stream,http,education
Platform: UNKNOWN
Requires-Dist: pillow
Requires-Dist: psutil
Requires-Dist: requests
Requires-Dist: requests[socks]
Requires-Dist: numpy
Requires-Dist: pyautogui
Requires-Dist: datetime
Requires-Dist: opencv-python
